toolsgram/__init__.py
toolsgram/error/__init__.py
toolsgram/image/__init__.py
toolsgram/model/__init__.py
toolsgram/system/__init__.py
toolsgram/telegram/__init__.py
toolsgram/web/__init__.py
toolsgram-0.0.1.dist-info/LICENSE
toolsgram-0.0.1.dist-info/METADATA
toolsgram-0.0.1.dist-info/WHEEL
toolsgram-0.0.1.dist-info/top_level.txt
toolsgram-0.0.1.dist-info/RECORD
