Metadata-Version: 2.1
Name: toolsgram
Version: 0.0.1
Summary: Python toolbox for Telegram bots development
Home-page: https://github.com/sergioteula/toolsgram
Author: Sergio Abad
Author-email: sergio.abad@bytelix.com
License: MIT
Platform: UNKNOWN
Classifier: Programming Language :: Python
Classifier: License :: OSI Approved :: MIT License
Classifier: Operating System :: OS Independent
Requires-Python: >=3.10
License-File: LICENSE
